di/__init__.py
di/_container.py
di/_task.py
di/_utils/__init__.py
di/_utils/concurrency.py
di/_utils/inspect.py
di/_utils/scope_map.py
di/_utils/types.py
di/api/__init__.py
di/api/dependencies.py
di/api/executor.py
di/api/providers.py
di/api/scopes.py
di/concurrency.py
di/dependent/__init__.py
di/dependent/_dependent.py
di/dependent/_injectable_type.py
di/dependent/_joined.py
di/exceptions.py
di/executors/__init__.py
di/executors/_async.py
di/executors/_sync.py
di/py.typed
di/typing.py
di-0.79.2.dist-info/LICENSE.txt
di-0.79.2.dist-info/METADATA
di-0.79.2.dist-info/WHEEL
di-0.79.2.dist-info/RECORD
