Metadata-Version: 2.1
Name: di
Version: 0.79.2
Summary: Dependency injection toolkit
Home-page: https://github.com/adriangb/di
License: MIT
Keywords: dependency-injection,inversion-of-control,SOLID,IoC,DI
Author: Adrian Garcia Badaracco
Author-email: adrian@adriangb.com
Requires-Python: >=3.8,<4
Classifier: Development Status :: 3 - Alpha
Classifier: Framework :: AsyncIO
Classifier: Framework :: Trio
Classifier: Intended Audience :: Developers
Classifier: License :: OSI Approved :: MIT License
Classifier: Programming Language :: Python :: 3
Classifier: Programming Language :: Python :: 3.8
Classifier: Programming Language :: Python :: 3.9
Classifier: Programming Language :: Python :: 3.10
Classifier: Programming Language :: Python :: 3.11
Classifier: Programming Language :: Python :: 3.12
Classifier: Topic :: Software Development
Classifier: Topic :: Software Development :: Libraries
Classifier: Topic :: Software Development :: Libraries :: Python Modules
Provides-Extra: anyio
Requires-Dist: anyio (>=3.5.0) ; extra == "anyio"
Requires-Dist: graphlib2 (>=0.4.1,<0.5.0)
Requires-Dist: typing-extensions (>=3) ; python_version < "3.9"
Project-URL: Documentation, https://www.adriangb.com/di
Project-URL: Repository, https://github.com/adriangb/di
